syncari/__init__.py
syncari/logger.py
syncari/models/__init__.py
syncari/models/core.py
syncari/models/request.py
syncari/models/schema.py
syncari/rest/__init__.py
syncari/rest/client.py
syncari/synapse/__init__.py
syncari/synapse/abstract_synapse.py
unit_tests/__init__.py
unit_tests/test_mock_synapse.py
unit_tests/test_not_supported_exception_synapse.py
unit_tests/test_response_validations.py
unit_tests/test_rest_client.py
syncari_sdk-1.3.22.dist-info/METADATA
syncari_sdk-1.3.22.dist-info/WHEEL
syncari_sdk-1.3.22.dist-info/top_level.txt
syncari_sdk-1.3.22.dist-info/RECORD
