Metadata-Version: 2.1
Name: syncari-sdk
Version: 1.3.22
Summary: Syncari Synapse Development Kit
Author: Syncari
Author-email: dev@syncari.com
License: TBD
Requires-Python: >=3.7.0
Requires-Dist: pydantic ~=1.6
Requires-Dist: requests
Requires-Dist: urllib3 ==1.26.0
Requires-Dist: backoff
Requires-Dist: google-cloud-logging ==3.10.0
